TDhelper/__init__.py
TDhelper/apiCore.py
TDhelper/reflect.py
TDhelper/Decorators/__init__.py
TDhelper/Decorators/log.py
TDhelper/Decorators/performance.py
TDhelper/Event/Event.py
TDhelper/Event/__init__.py
TDhelper/Event/classEvent/__init__.py
TDhelper/Event/classEvent/event.py
TDhelper/Event/classEvent/meta.py
TDhelper/Event/webEvent/Events.py
TDhelper/Event/webEvent/__init__.py
TDhelper/Event/webEvent/obsolete_Events.py
TDhelper/MagicCls/FieldsType.py
TDhelper/MagicCls/MagicMeta.py
TDhelper/MagicCls/__init__.py
TDhelper/MagicCls/model.py
TDhelper/MagicCls/test.py
TDhelper/Msg/AppPush.py
TDhelper/Msg/Config.py
TDhelper/Msg/Email.py
TDhelper/Msg/InterfaceMsg.py
TDhelper/Msg/SMS.py
TDhelper/Msg/__init__.py
TDhelper/Scheduler/__init__.py
TDhelper/Scheduler/base.py
TDhelper/Scheduler/example_scheduler.py
TDhelper/Scheduler/interface.py
TDhelper/Scheduler/log_config.py
TDhelper/Scheduler/service.py
TDhelper/Spider/__init__.py
TDhelper/Spider/cfg.py
TDhelper/Spider/contentExtraction.py
TDhelper/Spider/regex.py
TDhelper/Spider/spiderFactory.py
TDhelper/Spider/spiderPools.py
TDhelper/Spider/models/BadRequestModel.py
TDhelper/Spider/models/Cache_L1.py
TDhelper/Spider/models/Cache_L2.py
TDhelper/Spider/models/Cache_L2_Model.py
TDhelper/Spider/models/__init__.py
TDhelper/Spider/models/fingerprint.py
TDhelper/Spider/models/spider_event.py
TDhelper/Spider/models/status.py
TDhelper/bin/__init__.py
TDhelper/bin/globalvar.py
TDhelper/cache/__init__.py
TDhelper/cache/memcache.py
TDhelper/cache/pools.py
TDhelper/cache/ring.py
TDhelper/cache/webCache/__init__.py
TDhelper/cache/webCache/interface.py
TDhelper/cache/webCache/mongo.py
TDhelper/cache/webCache/redis.py
TDhelper/cache/webCache/webCacheFactory.py
TDhelper/db/__init__.py
TDhelper/db/Db/__init__.py
TDhelper/db/Db/base.py
TDhelper/db/Db/helper.py
TDhelper/db/factory/__init__.py
TDhelper/db/factory/interface.py
TDhelper/db/factory/mongodb/__init__.py
TDhelper/db/factory/mongodb/dirive.py
TDhelper/db/mongodb/__init__.py
TDhelper-2.8.34.dist-info/LICENSE
TDhelper-2.8.34.dist-info/METADATA
TDhelper-2.8.34.dist-info/WHEEL
TDhelper-2.8.34.dist-info/entry_points.txt
TDhelper-2.8.34.dist-info/top_level.txt
TDhelper-2.8.34.dist-info/RECORD
