Metadata-Version: 2.1
Name: TDhelper
Version: 2.8.34
Summary: fix rpc call don't know mater service bug.
Home-page: https://gitee.com/TonyDon/pyLib
Author: TangJing
Author-email: yeihizhi@163.com
License: Apache 2.0
Keywords: pip,TDhelper,featureextraction
License-File: LICENSE
Requires-Dist: crypto ==1.4.1
Requires-Dist: openpyxl ==3.1.2
Requires-Dist: pymongo ==4.3.3
Requires-Dist: requests ==2.28.2
Requires-Dist: six ==1.16.0
Requires-Dist: urllib3 ==1.26.15
Requires-Dist: mysql-connector >=2.2.9
